{
    "action": {
        "send_msg": "Send mail"
    },
    "folder": {
        "action": {
            "delete": "Delete address book",
            "delete_permanently": "Delete address book permanently",
            "edit": "Edit address book",
            "empty": {
                "folder": "Empty address book",
                "trash": "Empty trash"
            },
            "move": "Move address book",
            "new": "New address book"
        },
        "edit": {
            "body": {
                "properties": "Properties"
            }
        },
        "folder": "folder",
        "item": {
            "root": "Root"
        },
        "modal": {
            "delete": {
                "body": {
                    "message1": "Do you want to delete the address book selected? If you delete it, all the related content will be moved to trash and the address book will no longer be visible.",
                    "message2": "Do you want to delete permanently the address book selected? If you delete it, all the related content will be permanently removed and the address book will no longer be recoverable."
                },
                "footer": "Delete",
                "title": "Delete"
            },
            "edit": {
                "body": {
                    "contacts": "Contacts",
                    "item": {
                        "empty": "No path available",
                        "root": "root"
                    },
                    "name": "Address book name",
                    "select": "Select new destination",
                    "type": "Type"
                },
                "footer": "Edit",
                "title": "Edit"
            },
            "empty": {
                "body": {
                    "message1": "Do you want to empty the address book selected?",
                    "message2": "If you empty it, all the related content will be moved to trash."
                },
                "footer": "Empty",
                "title": "Empty"
            },
            "footer": {
                "cancel": "cancel"
            },
            "item": {
                "empty": "No items available"
            },
            "move": {
                "body": {
                    "message1": "Select an address book to move the considered one to:"
                },
                "footer": "Move",
                "input": {
                    "filter": "Filter address book"
                },
                "new": "New address Book",
                "title": "Move"
            },
            "new": {
                "body": {
                    "message1": "New address book name",
                    "message2": "Select an address book who will contain the newly created one:"
                },
                "footer": "Create",
                "input": {
                    "name": "Insert address book name",
                    "name_exist": "Name already exists in this path"
                },
                "title": "Create new address book"
            }
        }
    },
    "job": {
        "company": "Company",
        "department": "Department",
        "title": "Job Role"
    },
    "label": {
        "create": "New Contact",
        "edit": "Edit",
        "save": "Save"
    },
    "mail": "Email",
    "message": {
        "new_contact": "This contact will be created in the 'Contacts' folder"
    },
    "name": {
        "first_name": "First Name",
        "last_name": "Last Name",
        "middle_name": "Middle Name",
        "nickName": "Nickname",
        "prefix": "Prefix",
        "suffix": "Suffix"
    },
    "notes": "Notes",
    "section": {
        "field": {
            "city": "City",
            "country": "Country",
            "number": "Number",
            "postalCode": "PostalCode",
            "state": "State",
            "street": "Street",
            "url": "Website"
        },
        "title": {
            "address": "Address",
            "address_plural": "Address ({{count}})",
            "mail": "Email address",
            "phone_number": "Phone contact",
            "url": "Website",
            "url_plural": "Website ({{count}})"
        }
    },
    "select": {
        "default": "Select type"
    },
    "types": {
        "home": "home",
        "mobile": "mobile",
        "other": "other",
        "work": "work"
    }
}
